[
  {
    "flag": "https://twemoji.maxcdn.com/2/svg/1f1e6-1f1e8.svg",
    "country": "Ascension Island",
    "code": "ac",
    "visa": true,
    "typeVisa": ""
  },
  {
    "flag": "https://twemoji.maxcdn.com/2/svg/1f1e6-1f1e9.svg",
    "country": "Andorra",
    "code": "ad",
    "visa": false,
    "typeVisa": "90 days free"
  },
  {
    "flag": "https://twemoji.maxcdn.com/2/svg/1f1e6-1f1ea.svg",
    "country": "United Arab Emirates",
    "code": "ae",
    "visa": false,
    "typeVisa": "90 days free"
  },
  {
    "flag": "https://twemoji.maxcdn.com/2/svg/1f1e6-1f1eb.svg",
    "country": "Afghanistan",
    "code": "af",
    "visa": true,
    "typeVisa": ""
  },
  {
    "flag": "https://twemoji.maxcdn.com/2/svg/1f1e6-1f1ec.svg",
    "country": "Antigua & Barbuda",
    "code": "ag",
    "visa": false,
    "typeVisa": "90 days free"
  },
  {
    "flag": "https://twemoji.maxcdn.com/2/svg/1f1e6-1f1ee.svg",
    "country": "Anguilla",
    "code": "ai",
    "visa": true,
    "typeVisa": ""
  },
  {
    "flag": "https://twemoji.maxcdn.com/2/svg/1f1e6-1f1f1.svg",
    "country": "Albania",
    "code": "al",
    "visa": false,
    "typeVisa": "90 days free"
  },
  {
    "flag": "https://twemoji.maxcdn.com/2/svg/1f1e6-1f1f2.svg",
    "country": "Armenia",
    "code": "am",
    "visa": false,
    "typeVisa": "90 days free"
  },
  {
    "flag": "https://twemoji.maxcdn.com/2/svg/1f1e6-1f1f4.svg",
    "country": "Angola",
    "code": "ad",
    "visa": true,
    "typeVisa": ""
  },
  {
    "flag": "https://twemoji.maxcdn.com/2/svg/1f1e6-1f1f6.svg",
    "country": "Antarctica",
    "code": "aq",
    "visa": true,
    "typeVisa": ""
  },
  {
    "flag": "https://twemoji.maxcdn.com/2/svg/1f1e6-1f1f7.svg",
    "country": "Argentina",
    "code": "ar",
    "visa": false,
    "typeVisa": "no Visa"
  },
  {
    "flag": "https://twemoji.maxcdn.com/2/svg/1f1e6-1f1f8.svg",
    "country": "American Samoa",
    "code": "as",
    "visa": true,
    "typeVisa": ""
  },
  {
    "flag": "https://twemoji.maxcdn.com/2/svg/1f1e6-1f1f9.svg",
    "country": "Austria",
    "code": "at",
    "visa": true,
    "typeVisa": ""
  },
  {
    "flag": "https://twemoji.maxcdn.com/2/svg/1f1e6-1f1fa.svg",
    "country": "Australia",
    "code": "au",
    "visa": false,
    "typeVisa": "Electronic visa"
  },
  {
    "flag": "https://twemoji.maxcdn.com/2/svg/1f1e6-1f1fc.svg",
    "country": "Aruba",
    "code": "aw",
    "visa": true,
    "typeVisa": ""
  },
  {
    "flag": "https://twemoji.maxcdn.com/2/svg/1f1e6-1f1fd.svg",
    "country": "Åland Islands",
    "code": "ax",
    "visa": true,
    "typeVisa": ""
  },
  {
    "flag": "https://twemoji.maxcdn.com/2/svg/1f1e6-1f1ff.svg",
    "country": "Azerbaijan",
    "code": "az",
    "visa": true,
    "typeVisa": ""
  },
  {
    "flag": "https://twemoji.maxcdn.com/2/svg/1f1e7-1f1e6.svg",
    "country": "Bosnia & Herzegovina",
    "code": "ba",
    "visa": false,
    "typeVisa": "90 days free"
  },
  {
    "flag": "https://twemoji.maxcdn.com/2/svg/1f1e7-1f1e7.svg",
    "country": "Barbados",
    "code": "bb",
    "visa": false,
    "typeVisa": "90 days free"
  },
  {
    "flag": "https://twemoji.maxcdn.com/2/svg/1f1e7-1f1e9.svg",
    "country": "Bangladesh",
    "code": "bd",
    "visa": true,
    "typeVisa": ""
  },
  {
    "flag": "https://twemoji.maxcdn.com/2/svg/1f1e7-1f1ea.svg",
    "country": "Belgium",
    "code": "be",
    "visa": true,
    "typeVisa": ""
  },
  {
    "flag": "https://twemoji.maxcdn.com/2/svg/1f1e7-1f1eb.svg",
    "country": "Burkina Faso",
    "code": "bf",
    "visa": true,
    "typeVisa": ""
  },
  {
    "flag": "https://twemoji.maxcdn.com/2/svg/1f1e7-1f1ec.svg",
    "country": "Bulgaria",
    "code": "bg",
    "visa": true,
    "typeVisa": ""
  },
  {
    "flag": "https://twemoji.maxcdn.com/2/svg/1f1e7-1f1ed.svg",
    "country": "Bahrain",
    "code": "bh",
    "visa": true,
    "typeVisa": ""
  },
  {
    "flag": "https://twemoji.maxcdn.com/2/svg/1f1e7-1f1ee.svg",
    "country": "Burundi",
    "code": "bi",
    "visa": true,
    "typeVisa": ""
  },
  {
    "flag": "https://twemoji.maxcdn.com/2/svg/1f1e7-1f1ef.svg",
    "country": "Benin",
    "code": "bj",
    "visa": true,
    "typeVisa": ""
  },
  {
    "flag": "https://twemoji.maxcdn.com/2/svg/1f1e7-1f1f1.svg",
    "country": "St. Barthélemy",
    "code": "bl",
    "visa": true,
    "typeVisa": ""
  },
  {
    "flag": "https://twemoji.maxcdn.com/2/svg/1f1e7-1f1f2.svg",
    "country": "Bermuda",
    "code": "bm",
    "visa": true,
    "typeVisa": ""
  },
  {
    "flag": "https://twemoji.maxcdn.com/2/svg/1f1e7-1f1f3.svg",
    "country": "Brunei",
    "code": "bn",
    "visa": true,
    "typeVisa": ""
  },
  {
    "flag": "https://twemoji.maxcdn.com/2/svg/1f1e7-1f1f4.svg",
    "country": "Bolivia",
    "code": "bo",
    "visa": false,
    "typeVisa": "no Visa"
  },
  {
    "flag": "https://twemoji.maxcdn.com/2/svg/1f1e7-1f1f6.svg",
    "country": "Caribbean Netherlands",
    "visa": true,
    "typeVisa": ""
  },
  {
    "flag": "https://twemoji.maxcdn.com/2/svg/1f1e7-1f1f7.svg",
    "country": "Brazil",
    "code": "br",
    "visa": true,
    "typeVisa": ""
  },
  {
    "flag": "https://twemoji.maxcdn.com/2/svg/1f1e7-1f1f8.svg",
    "country": "Bahamas",
    "code": "bs",
    "visa": false,
    "typeVisa": "90 days free"
  },
  {
    "flag": "https://twemoji.maxcdn.com/2/svg/1f1e7-1f1f9.svg",
    "country": "Bhutan",
    "code": "bt",
    "visa": true,
    "typeVisa": ""
  },
  {
    "flag": "https://twemoji.maxcdn.com/2/svg/1f1e7-1f1fb.svg",
    "country": "Bouvet Island",
    "code": "bv",
    "visa": true,
    "typeVisa": ""
  },
  {
    "flag": "https://twemoji.maxcdn.com/2/svg/1f1e7-1f1fc.svg",
    "country": "Botswana",
    "code": "bw",
    "visa": false,
    "typeVisa": "90 days free"
  },
  {
    "flag": "https://twemoji.maxcdn.com/2/svg/1f1e7-1f1fe.svg",
    "country": "Belarus",
    "code": "by",
    "visa": false,
    "typeVisa": "90 days free"
  },
  {
    "flag": "https://twemoji.maxcdn.com/2/svg/1f1e7-1f1ff.svg",
    "country": "Belize",
    "code": "bz",
    "visa": false,
    "typeVisa": "90 days free"
  },
  {
    "flag": "https://twemoji.maxcdn.com/2/svg/1f1e8-1f1e6.svg",
    "country": "Canada",
    "code": "ca",
    "visa": false,
    "typeVisa": "Electronic visa"
  },
  {
    "flag": "https://twemoji.maxcdn.com/2/svg/1f1e8-1f1e8.svg",
    "country": "Cocos (Keeling) Islands",
    "code": "cc",
    "visa": true,
    "typeVisa": ""
  },
  {
    "flag": "https://twemoji.maxcdn.com/2/svg/1f1e8-1f1e9.svg",
    "country": "Congo - Kinshasa",
    "code": "cg",
    "visa": true,
    "typeVisa": ""
  },
  {
    "flag": "https://twemoji.maxcdn.com/2/svg/1f1e8-1f1eb.svg",
    "country": "Central African Republic",
    "code": "cf",
    "visa": true,
    "typeVisa": ""
  },
  {
    "flag": "https://twemoji.maxcdn.com/2/svg/1f1e8-1f1ec.svg",
    "country": "Congo - Brazzaville",
    "code": "cd",
    "visa": true,
    "typeVisa": ""
  },
  {
    "flag": "https://twemoji.maxcdn.com/2/svg/1f1e8-1f1ed.svg",
    "country": "Switzerland",
    "code": "ch",
    "visa": false,
    "typeVisa": "90 days free"
  },
  {
    "flag": "https://twemoji.maxcdn.com/2/svg/1f1e8-1f1ee.svg",
    "country": "Côte d’Ivoire",
    "code": "ci",
    "visa": true,
    "typeVisa": ""
  },
  {
    "flag": "https://twemoji.maxcdn.com/2/svg/1f1e8-1f1f0.svg",
    "country": "Cook Islands",
    "code": "ck",
    "visa": true,
    "typeVisa": ""
  },
  {
    "flag": "https://twemoji.maxcdn.com/2/svg/1f1e8-1f1f1.svg",
    "country": "Chile",
    "code": "cl",
    "visa": false,
    "typeVisa": "no Visa"
  },
  {
    "flag": "https://twemoji.maxcdn.com/2/svg/1f1e8-1f1f2.svg",
    "country": "Cameroon",
    "code": "cm",
    "visa": true,
    "typeVisa": ""
  },
  {
    "flag": "https://twemoji.maxcdn.com/2/svg/1f1e8-1f1f3.svg",
    "country": "China",
    "code": "cn",
    "visa": true,
    "typeVisa": ""
  },
  {
    "flag": "https://twemoji.maxcdn.com/2/svg/1f1e8-1f1f4.svg",
    "country": "Colombia",
    "code": "co",
    "visa": false,
    "typeVisa": "no Visa"
  },
  {
    "flag": "https://twemoji.maxcdn.com/2/svg/1f1e8-1f1f5.svg",
    "country": "Clipperton Island",
    "code": "cp",
    "visa": true,
    "typeVisa": ""
  },
  {
    "flag": "https://twemoji.maxcdn.com/2/svg/1f1e8-1f1f7.svg",
    "country": "Costa Rica",
    "code": "cr",
    "visa": false,
    "typeVisa": "90 days free"
  },
  {
    "flag": "https://twemoji.maxcdn.com/2/svg/1f1e8-1f1fa.svg",
    "country": "Cuba",
    "code": "cu",
    "visa": true,
    "typeVisa": ""
  },
  {
    "flag": "https://twemoji.maxcdn.com/2/svg/1f1e8-1f1fb.svg",
    "country": "Cape Verde",
    "code": "cv",
    "visa": true,
    "typeVisa": ""
  },
  {
    "flag": "https://twemoji.maxcdn.com/2/svg/1f1e8-1f1fc.svg",
    "country": "Curaçao",
    "code": "cw",
    "visa": true,
    "typeVisa": ""
  },
  {
    "flag": "https://twemoji.maxcdn.com/2/svg/1f1e8-1f1fd.svg",
    "country": "Christmas Island",
    "code": "cx",
    "visa": true,
    "typeVisa": ""
  },
  {
    "flag": "https://twemoji.maxcdn.com/2/svg/1f1e8-1f1fe.svg",
    "country": "Cyprus",
    "code": "cy",
    "visa": true,
    "typeVisa": ""
  },
  {
    "flag": "https://twemoji.maxcdn.com/2/svg/1f1e8-1f1ff.svg",
    "country": "Czechia",
    "code": "cz",
    "visa": true,
    "typeVisa": ""
  },
  {
    "flag": "https://twemoji.maxcdn.com/2/svg/1f1e9-1f1ea.svg",
    "country": "Germany",
    "code": "de",
    "visa": true,
    "typeVisa": ""
  },
  {
    "flag": "https://twemoji.maxcdn.com/2/svg/1f1e9-1f1ec.svg",
    "country": "Diego Garcia",
    "code": "dg",
    "visa": true,
    "typeVisa": ""
  },
  {
    "flag": "https://twemoji.maxcdn.com/2/svg/1f1e9-1f1ef.svg",
    "country": "Djibouti",
    "code": "dj",
    "visa": true,
    "typeVisa": ""
  },
  {
    "flag": "https://twemoji.maxcdn.com/2/svg/1f1e9-1f1f0.svg",
    "country": "Denmark",
    "code": "dk",
    "visa": true,
    "typeVisa": ""
  },
  {
    "flag": "https://twemoji.maxcdn.com/2/svg/1f1e9-1f1f2.svg",
    "country": "Dominica",
    "code": "dm",
    "visa": false,
    "typeVisa": "90 days free"
  },
  {
    "flag": "https://twemoji.maxcdn.com/2/svg/1f1e9-1f1f4.svg",
    "country": "Dominican Republic",
    "code": "do",
    "visa": false,
    "typeVisa": "90 days free"
  },
  {
    "flag": "https://twemoji.maxcdn.com/2/svg/1f1e9-1f1ff.svg",
    "country": "Algeria",
    "code": "dz",
    "visa": true,
    "typeVisa": ""
  },
  {
    "flag": "https://twemoji.maxcdn.com/2/svg/1f1ea-1f1e6.svg",
    "country": "Ceuta & Melilla",
    "code": "ea",
    "visa": true,
    "typeVisa": ""
  },
  {
    "flag": "https://twemoji.maxcdn.com/2/svg/1f1ea-1f1e8.svg",
    "country": "Ecuador",
    "code": "ec",
    "visa": false,
    "typeVisa": "no Visa"
  },
  {
    "flag": "https://twemoji.maxcdn.com/2/svg/1f1ea-1f1ea.svg",
    "country": "Estonia",
    "code": "ee",
    "visa": true,
    "typeVisa": ""
  },
  {
    "flag": "https://twemoji.maxcdn.com/2/svg/1f1ea-1f1ec.svg",
    "country": "Egypt",
    "code": "eg",
    "visa": true,
    "typeVisa": ""
  },
  {
    "flag": "https://twemoji.maxcdn.com/2/svg/1f1ea-1f1ed.svg",
    "country": "Western Sahara",
    "code": "eh",
    "visa": true,
    "typeVisa": ""
  },
  {
    "flag": "https://twemoji.maxcdn.com/2/svg/1f1ea-1f1f7.svg",
    "country": "Eritrea",
    "code": "er",
    "visa": true,
    "typeVisa": ""
  },
  {
    "flag": "https://twemoji.maxcdn.com/2/svg/1f1ea-1f1f8.svg",
    "country": "Spain",
    "code": "es",
    "visa": true,
    "typeVisa": ""
  },
  {
    "flag": "https://twemoji.maxcdn.com/2/svg/1f1ea-1f1f9.svg",
    "country": "Ethiopia",
    "code": "et",
    "visa": true,
    "typeVisa": ""
  },
  {
    "flag": "https://twemoji.maxcdn.com/2/svg/1f1ea-1f1fa.svg",
    "country": "European Union",
    "code": "eu",
    "visa": false,
    "typeVisa": "90 days free"
  },
  {
    "flag": "https://twemoji.maxcdn.com/2/svg/1f1eb-1f1ee.svg",
    "country": "Finland",
    "code": "fi",
    "visa": true,
    "typeVisa": ""
  },
  {
    "flag": "https://twemoji.maxcdn.com/2/svg/1f1eb-1f1ef.svg",
    "country": "Fiji",
    "code": "fj",
    "visa": false,
    "typeVisa": "90 days free"
  },
  {
    "flag": "https://twemoji.maxcdn.com/2/svg/1f1eb-1f1f0.svg",
    "country": "Falkland Islands",
    "code": "fk",
    "visa": true,
    "typeVisa": ""
  },
  {
    "flag": "https://twemoji.maxcdn.com/2/svg/1f1eb-1f1f2.svg",
    "country": "Micronesia",
    "code": "fm",
    "visa": false,
    "typeVisa": "90 days free"
  },
  {
    "flag": "https://twemoji.maxcdn.com/2/svg/1f1eb-1f1f4.svg",
    "country": "Faroe Islands",
    "code": "fo",
    "visa": true,
    "typeVisa": ""
  },
  {
    "flag": "https://twemoji.maxcdn.com/2/svg/1f1eb-1f1f7.svg",
    "country": "France",
    "code": "fr",
    "visa": true,
    "typeVisa": ""
  },
  {
    "flag": "https://twemoji.maxcdn.com/2/svg/1f1ec-1f1e6.svg",
    "country": "Gabon",
    "code": "ga",
    "visa": true,
    "typeVisa": ""
  },
  {
    "flag": "https://twemoji.maxcdn.com/2/svg/1f1ec-1f1e7.svg",
    "country": "United Kingdom",
    "code": "gb",
    "visa": false,
    "typeVisa": "90 days free"
  },
  {
    "flag": "https://twemoji.maxcdn.com/2/svg/1f1ec-1f1e9.svg",
    "country": "Grenada",
    "code": "gd",
    "visa": false,
    "typeVisa": "90 days free"
  },
  {
    "flag": "https://twemoji.maxcdn.com/2/svg/1f1ec-1f1ea.svg",
    "country": "Georgia",
    "code": "ge",
    "visa": false,
    "typeVisa": "90 days free"
  },
  {
    "flag": "https://twemoji.maxcdn.com/2/svg/1f1ec-1f1eb.svg",
    "country": "French Guiana",
    "code": "gf",
    "visa": true,
    "typeVisa": ""
  },
  {
    "flag": "https://twemoji.maxcdn.com/2/svg/1f1ec-1f1ec.svg",
    "country": "Guernsey",
    "code": "gg",
    "visa": true,
    "typeVisa": ""
  },
  {
    "flag": "https://twemoji.maxcdn.com/2/svg/1f1ec-1f1ed.svg",
    "country": "Ghana",
    "code": "gh",
    "visa": true,
    "typeVisa": ""
  },
  {
    "flag": "https://twemoji.maxcdn.com/2/svg/1f1ec-1f1ee.svg",
    "country": "Gibraltar",
    "code": "gi",
    "visa": true,
    "typeVisa": ""
  },
  {
    "flag": "https://twemoji.maxcdn.com/2/svg/1f1ec-1f1f1.svg",
    "country": "Greenland",
    "code": "gl",
    "visa": true,
    "typeVisa": ""
  },
  {
    "flag": "https://twemoji.maxcdn.com/2/svg/1f1ec-1f1f2.svg",
    "country": "Gambia",
    "code": "gm",
    "visa": true,
    "typeVisa": ""
  },
  {
    "flag": "https://twemoji.maxcdn.com/2/svg/1f1ec-1f1f3.svg",
    "country": "Guinea",
    "code": "gn",
    "visa": true,
    "typeVisa": ""
  },
  {
    "flag": "https://twemoji.maxcdn.com/2/svg/1f1ec-1f1f5.svg",
    "country": "Guadeloupe",
    "code": "gp",
    "visa": true,
    "typeVisa": ""
  },
  {
    "flag": "https://twemoji.maxcdn.com/2/svg/1f1ec-1f1f6.svg",
    "country": "Equatorial Guinea",
    "code": "gq",
    "visa": true,
    "typeVisa": ""
  },
  {
    "flag": "https://twemoji.maxcdn.com/2/svg/1f1ec-1f1f7.svg",
    "country": "Greece",
    "code": "gr",
    "visa": true,
    "typeVisa": ""
  },
  {
    "flag": "https://twemoji.maxcdn.com/2/svg/1f1ec-1f1f8.svg",
    "country": "South Georgia & South', Sandwich Islands",
    "code": "gs",
    "visa": true,
    "typeVisa": ""
  },
  {
    "flag": "https://twemoji.maxcdn.com/2/svg/1f1ec-1f1f9.svg",
    "country": "Guatemala",
    "code": "gt",
    "visa": false,
    "typeVisa": "90 days free"
  },
  {
    "flag": "https://twemoji.maxcdn.com/2/svg/1f1ec-1f1fa.svg",
    "country": "Guam",
    "code": "gu",
    "visa": true,
    "typeVisa": ""
  },
  {
    "flag": "https://twemoji.maxcdn.com/2/svg/1f1ec-1f1fc.svg",
    "country": "Guinea-Bissau",
    "code": "gw",
    "visa": true,
    "typeVisa": ""
  },
  {
    "flag": "https://twemoji.maxcdn.com/2/svg/1f1ec-1f1fe.svg",
    "country": "Guyana",
    "code": "gy",
    "visa": false,
    "typeVisa": "90 days free"
  },
  {
    "flag": "https://twemoji.maxcdn.com/2/svg/1f1ed-1f1f0.svg",
    "country": "Hong Kong SAR China",
    "code": "hk",
    "visa": false,
    "typeVisa": "90 days free"
  },
  {
    "flag": "https://twemoji.maxcdn.com/2/svg/1f1ed-1f1f2.svg",
    "country": "Heard & McDonald Islands",
    "code": "hm",
    "visa": true,
    "typeVisa": ""
  },
  {
    "flag": "https://twemoji.maxcdn.com/2/svg/1f1ed-1f1f3.svg",
    "country": "Honduras",
    "code": "hn",
    "visa": false,
    "typeVisa": "90 days free"
  },
  {
    "flag": "https://twemoji.maxcdn.com/2/svg/1f1ed-1f1f7.svg",
    "country": "Croatia",
    "code": "hr",
    "visa": true,
    "typeVisa": ""
  },
  {
    "flag": "https://twemoji.maxcdn.com/2/svg/1f1ed-1f1f9.svg",
    "country": "Haiti",
    "code": "ht",
    "visa": true,
    "typeVisa": ""
  },
  {
    "flag": "https://twemoji.maxcdn.com/2/svg/1f1ed-1f1fa.svg",
    "country": "Hungary",
    "code": "hu",
    "visa": true,
    "typeVisa": ""
  },
  {
    "flag": "https://twemoji.maxcdn.com/2/svg/1f1ee-1f1e8.svg",
    "country": "Canary Islands",
    "code": "ic",
    "visa": true,
    "typeVisa": ""
  },
  {
    "flag": "https://twemoji.maxcdn.com/2/svg/1f1ee-1f1e9.svg",
    "country": "Indonesia",
    "code": "id",
    "visa": false,
    "typeVisa": "90 days free"
  },
  {
    "flag": "https://twemoji.maxcdn.com/2/svg/1f1ee-1f1ea.svg",
    "country": "Ireland",
    "code": "ie",
    "visa": true,
    "typeVisa": ""
  },
  {
    "flag": "https://twemoji.maxcdn.com/2/svg/1f1ee-1f1f1.svg",
    "country": "Israel",
    "code": "il",
    "visa": false,
    "typeVisa": "90 days free"
  },
  {
    "flag": "https://twemoji.maxcdn.com/2/svg/1f1ee-1f1f2.svg",
    "country": "Isle of Man",
    "code": "im",
    "visa": true,
    "typeVisa": ""
  },
  {
    "flag": "https://twemoji.maxcdn.com/2/svg/1f1ee-1f1f3.svg",
    "country": "India",
    "code": "in",
    "visa": true,
    "typeVisa": ""
  },
  {
    "flag": "https://twemoji.maxcdn.com/2/svg/1f1ee-1f1f4.svg",
    "country": "British Indian Ocean Territory",
    "code": "io",
    "visa": true,
    "typeVisa": ""
  },
  {
    "flag": "https://twemoji.maxcdn.com/2/svg/1f1ee-1f1f6.svg",
    "country": "Iraq",
    "code": "iq",
    "visa": true,
    "typeVisa": ""
  },
  {
    "flag": "https://twemoji.maxcdn.com/2/svg/1f1ee-1f1f7.svg",
    "country": "Iran",
    "visa": true,
    "typeVisa": ""
  },
  {
    "flag": "https://twemoji.maxcdn.com/2/svg/1f1ee-1f1f8.svg",
    "country": "Iceland",
    "code": "is",
    "visa": false,
    "typeVisa": "90 days free"
  },
  {
    "flag": "https://twemoji.maxcdn.com/2/svg/1f1ee-1f1f9.svg",
    "country": "Italy",
    "code": "it",
    "visa": true,
    "typeVisa": ""
  },
  {
    "flag": "https://twemoji.maxcdn.com/2/svg/1f1ef-1f1ea.svg",
    "country": "Jersey",
    "code": "je",
    "visa": true,
    "typeVisa": ""
  },
  {
    "flag": "https://twemoji.maxcdn.com/2/svg/1f1ef-1f1f2.svg",
    "country": "Jamaica",
    "code": "jm",
    "visa": false,
    "typeVisa": "90 days free"
  },
  {
    "flag": "https://twemoji.maxcdn.com/2/svg/1f1ef-1f1f4.svg",
    "country": "Jordan",
    "code": "jo",
    "visa": true,
    "typeVisa": ""
  },
  {
    "flag": "https://twemoji.maxcdn.com/2/svg/1f1ef-1f1f5.svg",
    "country": "Japan",
    "code": "jp",
    "visa": false,
    "typeVisa": "90 days free"
  },
  {
    "flag": "https://twemoji.maxcdn.com/2/svg/1f1f0-1f1ea.svg",
    "country": "Kenya",
    "code": "ke",
    "visa": true,
    "typeVisa": ""
  },
  {
    "flag": "https://twemoji.maxcdn.com/2/svg/1f1f0-1f1ec.svg",
    "country": "Kyrgyzstan",
    "code": "kg",
    "visa": true,
    "typeVisa": ""
  },
  {
    "flag": "https://twemoji.maxcdn.com/2/svg/1f1f0-1f1ed.svg",
    "country": "Cambodia",
    "code": "kh",
    "visa": true,
    "typeVisa": ""
  },
  {
    "flag": "https://twemoji.maxcdn.com/2/svg/1f1f0-1f1ee.svg",
    "country": "Kiribati",
    "code": "ki",
    "visa": true,
    "typeVisa": ""
  },
  {
    "flag": "https://twemoji.maxcdn.com/2/svg/1f1f0-1f1f2.svg",
    "country": "Comoros",
    "code": "km",
    "visa": true,
    "typeVisa": ""
  },
  {
    "flag": "https://twemoji.maxcdn.com/2/svg/1f1f0-1f1f3.svg",
    "country": "St. Kitts & Nevis",
    "code": "kn",
    "visa": true,
    "typeVisa": ""
  },
  {
    "flag": "https://twemoji.maxcdn.com/2/svg/1f1f0-1f1f5.svg",
    "country": "North Korea",
    "code": "kp",
    "visa": true,
    "typeVisa": ""
  },
  {
    "flag": "https://twemoji.maxcdn.com/2/svg/1f1f0-1f1f7.svg",
    "country": "South Korea",
    "code": "kr",
    "visa": false,
    "typeVisa": "90 days free"
  },
  {
    "flag": "https://twemoji.maxcdn.com/2/svg/1f1f0-1f1fc.svg",
    "country": "Kuwait",
    "code": "kw",
    "visa": true,
    "typeVisa": ""
  },
  {
    "flag": "https://twemoji.maxcdn.com/2/svg/1f1f0-1f1fe.svg",
    "country": "Cayman Islands",
    "code": "ky",
    "visa": true,
    "typeVisa": ""
  },
  {
    "flag": "https://twemoji.maxcdn.com/2/svg/1f1f0-1f1ff.svg",
    "country": "Kazakhstan",
    "code": "kz",
    "visa": false,
    "typeVisa": "90 days free"
  },
  {
    "flag": "https://twemoji.maxcdn.com/2/svg/1f1f1-1f1e6.svg",
    "country": "Laos",
    "code": "la",
    "visa": true,
    "typeVisa": ""
  },
  {
    "flag": "https://twemoji.maxcdn.com/2/svg/1f1f1-1f1e7.svg",
    "country": "Lebanon",
    "code": "lb",
    "visa": true,
    "typeVisa": ""
  },
  {
    "flag": "https://twemoji.maxcdn.com/2/svg/1f1f1-1f1e8.svg",
    "country": "St. Lucia",
    "code": "lc",
    "visa": true,
    "typeVisa": ""
  },
  {
    "flag": "https://twemoji.maxcdn.com/2/svg/1f1f1-1f1ee.svg",
    "country": "Liechtenstein",
    "code": "li",
    "visa": false,
    "typeVisa": "90 days free"
  },
  {
    "flag": "https://twemoji.maxcdn.com/2/svg/1f1f1-1f1f0.svg",
    "country": "Sri Lanka",
    "code": "lk",
    "visa": true,
    "typeVisa": ""
  },
  {
    "flag": "https://twemoji.maxcdn.com/2/svg/1f1f1-1f1f7.svg",
    "country": "Liberia",
    "code": "lr",
    "visa": true,
    "typeVisa": ""
  },
  {
    "flag": "https://twemoji.maxcdn.com/2/svg/1f1f1-1f1f8.svg",
    "country": "Lesotho",
    "code": "ls",
    "visa": true,
    "typeVisa": ""
  },
  {
    "flag": "https://twemoji.maxcdn.com/2/svg/1f1f1-1f1f9.svg",
    "country": "Lithuania",
    "code": "lt",
    "visa": true,
    "typeVisa": ""
  },
  {
    "flag": "https://twemoji.maxcdn.com/2/svg/1f1f1-1f1fa.svg",
    "country": "Luxembourg",
    "code": "lu",
    "visa": true,
    "typeVisa": ""
  },
  {
    "flag": "https://twemoji.maxcdn.com/2/svg/1f1f1-1f1fb.svg",
    "country": "Latvia",
    "code": "lv",
    "visa": true,
    "typeVisa": ""
  },
  {
    "flag": "https://twemoji.maxcdn.com/2/svg/1f1f1-1f1fe.svg",
    "country": "Libya",
    "code": "ly",
    "visa": true,
    "typeVisa": ""
  },
  {
    "flag": "https://twemoji.maxcdn.com/2/svg/1f1f2-1f1e6.svg",
    "country": "Morocco",
    "code": "ma",
    "visa": false,
    "typeVisa": "90 days free"
  },
  {
    "flag": "https://twemoji.maxcdn.com/2/svg/1f1f2-1f1e8.svg",
    "country": "Monaco",
    "code": "mc",
    "visa": false,
    "typeVisa": "90 days free"
  },
  {
    "flag": "https://twemoji.maxcdn.com/2/svg/1f1f2-1f1e9.svg",
    "country": "Moldova",
    "code": "md",
    "visa": false,
    "typeVisa": "90 days free"
  },
  {
    "flag": "https://twemoji.maxcdn.com/2/svg/1f1f2-1f1ea.svg",
    "country": "Montenegro",
    "code": "me",
    "visa": false,
    "typeVisa": "90 days free"
  },
  {
    "flag": "https://twemoji.maxcdn.com/2/svg/1f1f2-1f1eb.svg",
    "country": "St. Martin",
    "code": "mf",
    "visa": true,
    "typeVisa": ""
  },
  {
    "flag": "https://twemoji.maxcdn.com/2/svg/1f1f2-1f1ec.svg",
    "country": "Madagascar",
    "code": "mg",
    "visa": true,
    "typeVisa": ""
  },
  {
    "flag": "https://twemoji.maxcdn.com/2/svg/1f1f2-1f1ed.svg",
    "country": "Marshall Islands",
    "code": "mh",
    "visa": true,
    "typeVisa": ""
  },
  {
    "flag": "https://twemoji.maxcdn.com/2/svg/1f1f2-1f1f0.svg",
    "country": "North Macedonia",
    "code": "mk",
    "visa": false,
    "typeVisa": "90 days free"
  },
  {
    "flag": "https://twemoji.maxcdn.com/2/svg/1f1f2-1f1f1.svg",
    "country": "Mali",
    "code": "ml",
    "visa": true,
    "typeVisa": ""
  },
  {
    "flag": "https://twemoji.maxcdn.com/2/svg/1f1f2-1f1f2.svg",
    "country": "Myanmar (Burma)",
    "code": "mm",
    "visa": true,
    "typeVisa": ""
  },
  {
    "flag": "https://twemoji.maxcdn.com/2/svg/1f1f2-1f1f3.svg",
    "country": "Mongolia",
    "code": "mn",
    "visa": false,
    "typeVisa": "90 days free"
  },
  {
    "flag": "https://twemoji.maxcdn.com/2/svg/1f1f2-1f1f4.svg",
    "country": "Macao Sar China",
    "code": "mo",
    "visa": true,
    "typeVisa": ""
  },
  {
    "flag": "https://twemoji.maxcdn.com/2/svg/1f1f2-1f1f5.svg",
    "country": "Northern Mariana Islands",
    "code": "mp",
    "visa": true,
    "typeVisa": ""
  },
  {
    "flag": "https://twemoji.maxcdn.com/2/svg/1f1f2-1f1f6.svg",
    "country": "Martinique",
    "code": "mq",
    "visa": true,
    "typeVisa": ""
  },
  {
    "flag": "https://twemoji.maxcdn.com/2/svg/1f1f2-1f1f7.svg",
    "country": "Mauritania",
    "code": "mr",
    "visa": true,
    "typeVisa": ""
  },
  {
    "flag": "https://twemoji.maxcdn.com/2/svg/1f1f2-1f1f8.svg",
    "country": "Montserrat",
    "code": "ms",
    "visa": true,
    "typeVisa": ""
  },
  {
    "flag": "https://twemoji.maxcdn.com/2/svg/1f1f2-1f1f9.svg",
    "country": "Malta",
    "code": "mt",
    "visa": true,
    "typeVisa": ""
  },
  {
    "flag": "https://twemoji.maxcdn.com/2/svg/1f1f2-1f1fa.svg",
    "country": "Mauritius",
    "code": "mu",
    "visa": true,
    "typeVisa": ""
  },
  {
    "flag": "https://twemoji.maxcdn.com/2/svg/1f1f2-1f1fb.svg",
    "country": "Maldives",
    "code": "mv",
    "visa": true,
    "typeVisa": ""
  },
  {
    "flag": "https://twemoji.maxcdn.com/2/svg/1f1f2-1f1fc.svg",
    "country": "Malawi",
    "code": "mw",
    "visa": true,
    "typeVisa": ""
  },
  {
    "flag": "https://twemoji.maxcdn.com/2/svg/1f1f2-1f1fd.svg",
    "country": "Mexico",
    "code": "mx",
    "visa": false,
    "typeVisa": "90 days free"
  },
  {
    "flag": "https://twemoji.maxcdn.com/2/svg/1f1f2-1f1fe.svg",
    "country": "Malaysia",
    "code": "my",
    "visa": false,
    "typeVisa": "90 days free"
  },
  {
    "flag": "https://twemoji.maxcdn.com/2/svg/1f1f2-1f1ff.svg",
    "country": "Mozambique",
    "code": "mz",
    "visa": true,
    "typeVisa": ""
  },
  {
    "flag": "https://twemoji.maxcdn.com/2/svg/1f1f3-1f1e6.svg",
    "country": "Namibia",
    "code": "na",
    "visa": false,
    "typeVisa": "90 days free"
  },
  {
    "flag": "https://twemoji.maxcdn.com/2/svg/1f1f3-1f1e8.svg",
    "country": "New Caledonia",
    "code": "nc",
    "visa": true,
    "typeVisa": ""
  },
  {
    "flag": "https://twemoji.maxcdn.com/2/svg/1f1f3-1f1ea.svg",
    "country": "Niger",
    "code": "ne",
    "visa": true,
    "typeVisa": ""
  },
  {
    "flag": "https://twemoji.maxcdn.com/2/svg/1f1f3-1f1eb.svg",
    "country": "Norfolk Island",
    "code": "nf",
    "visa": true,
    "typeVisa": ""
  },
  {
    "flag": "https://twemoji.maxcdn.com/2/svg/1f1f3-1f1ec.svg",
    "country": "Nigeria",
    "code": "ng",
    "visa": true,
    "typeVisa": ""
  },
  {
    "flag": "https://twemoji.maxcdn.com/2/svg/1f1f3-1f1ee.svg",
    "country": "Nicaragua",
    "code": "ni",
    "visa": false,
    "typeVisa": "90 days free"
  },
  {
    "flag": "https://twemoji.maxcdn.com/2/svg/1f1f3-1f1f1.svg",
    "country": "Netherlands",
    "code": "nl",
    "visa": true,
    "typeVisa": ""
  },
  {
    "flag": "https://twemoji.maxcdn.com/2/svg/1f1f3-1f1f4.svg",
    "country": "Norway",
    "code": "no",
    "visa": false,
    "typeVisa": "90 days free"
  },
  {
    "flag": "https://twemoji.maxcdn.com/2/svg/1f1f3-1f1f5.svg",
    "country": "Nepal",
    "code": "np",
    "visa": true,
    "typeVisa": ""
  },
  {
    "flag": "https://twemoji.maxcdn.com/2/svg/1f1f3-1f1f7.svg",
    "country": "Nauru",
    "code": "nr",
    "visa": true,
    "typeVisa": ""
  },
  {
    "flag": "https://twemoji.maxcdn.com/2/svg/1f1f3-1f1fa.svg",
    "country": "Niue",
    "code": "nu",
    "visa": true,
    "typeVisa": ""
  },
  {
    "flag": "https://twemoji.maxcdn.com/2/svg/1f1f3-1f1ff.svg",
    "country": "New Zealand",
    "code": "nz",
    "visa": false,
    "typeVisa": "90 days free"
  },
  {
    "flag": "https://twemoji.maxcdn.com/2/svg/1f1f4-1f1f2.svg",
    "country": "Oman",
    "code": "om",
    "visa": true,
    "typeVisa": ""
  },
  {
    "flag": "https://twemoji.maxcdn.com/2/svg/1f1f5-1f1e6.svg",
    "country": "Panama",
    "code": "pa",
    "visa": false,
    "typeVisa": "90 days free"
  },
  {
    "flag": "https://twemoji.maxcdn.com/2/svg/1f1f5-1f1ea.svg",
    "country": "Peru",
    "code": "pe",
    "visa": false,
    "typeVisa": "no Visa"
  },
  {
    "flag": "https://twemoji.maxcdn.com/2/svg/1f1f5-1f1eb.svg",
    "country": "French Polynesia",
    "code": "pf",
    "visa": true,
    "typeVisa": ""
  },
  {
    "flag": "https://twemoji.maxcdn.com/2/svg/1f1f5-1f1ec.svg",
    "country": "Papua New Guinea",
    "code": "pg",
    "visa": true,
    "typeVisa": ""
  },
  {
    "flag": "https://twemoji.maxcdn.com/2/svg/1f1f5-1f1ed.svg",
    "country": "Philippines",
    "code": "ph",
    "visa": false,
    "typeVisa": "90 days free"
  },
  {
    "flag": "https://twemoji.maxcdn.com/2/svg/1f1f5-1f1f0.svg",
    "country": "Pakistan",
    "code": "pk",
    "visa": true,
    "typeVisa": ""
  },
  {
    "flag": "https://twemoji.maxcdn.com/2/svg/1f1f5-1f1f1.svg",
    "country": "Poland",
    "code": "pl",
    "visa": true,
    "typeVisa": ""
  },
  {
    "flag": "https://twemoji.maxcdn.com/2/svg/1f1f5-1f1f2.svg",
    "country": "St. Pierre & Miquelon",
    "code": "pm",
    "visa": true,
    "typeVisa": ""
  },
  {
    "flag": "https://twemoji.maxcdn.com/2/svg/1f1f5-1f1f3.svg",
    "country": "Pitcairn Islands",
    "code": "pn",
    "visa": true,
    "typeVisa": ""
  },
  {
    "flag": "https://twemoji.maxcdn.com/2/svg/1f1f5-1f1f7.svg",
    "country": "Puerto Rico",
    "code": "pr",
    "visa": true,
    "typeVisa": ""
  },
  {
    "flag": "https://twemoji.maxcdn.com/2/svg/1f1f5-1f1f8.svg",
    "country": "Palestinian Territories",
    "code": "ps",
    "visa": true,
    "typeVisa": ""
  },
  {
    "flag": "https://twemoji.maxcdn.com/2/svg/1f1f5-1f1f9.svg",
    "country": "Portugal",
    "code": "pt",
    "visa": true,
    "typeVisa": ""
  },
  {
    "flag": "https://twemoji.maxcdn.com/2/svg/1f1f5-1f1fc.svg",
    "country": "Palau",
    "code": "pw",
    "visa": true,
    "typeVisa": ""
  },
  {
    "flag": "https://twemoji.maxcdn.com/2/svg/1f1f5-1f1fe.svg",
    "country": "Paraguay",
    "code": "py",
    "visa": false,
    "typeVisa": "no Visa"
  },
  {
    "flag": "https://twemoji.maxcdn.com/2/svg/1f1f6-1f1e6.svg",
    "country": "Qatar",
    "code": "qa",
    "visa": false,
    "typeVisa": "90 days free"
  },
  {
    "flag": "https://twemoji.maxcdn.com/2/svg/1f1f7-1f1ea.svg",
    "country": "Réunion",
    "code": "re",
    "visa": true,
    "typeVisa": ""
  },
  {
    "flag": "https://twemoji.maxcdn.com/2/svg/1f1f7-1f1f4.svg",
    "country": "Romania",
    "code": "ro",
    "visa": true,
    "typeVisa": ""
  },
  {
    "flag": "https://twemoji.maxcdn.com/2/svg/1f1f7-1f1f8.svg",
    "country": "Serbia",
    "code": "yu",
    "visa": false,
    "typeVisa": "90 days free"
  },
  {
    "flag": "https://twemoji.maxcdn.com/2/svg/1f1f7-1f1fa.svg",
    "country": "Russia",
    "code": "ru",
    "visa": false,
    "typeVisa": "90 days free"
  },
  {
    "flag": "https://twemoji.maxcdn.com/2/svg/1f1f7-1f1fc.svg",
    "country": "Rwanda",
    "code": "rw",
    "visa": true,
    "typeVisa": ""
  },
  {
    "flag": "https://twemoji.maxcdn.com/2/svg/1f1f8-1f1e6.svg",
    "country": "Saudi Arabia",
    "code": "sa",
    "visa": true,
    "typeVisa": ""
  },
  {
    "flag": "https://twemoji.maxcdn.com/2/svg/1f1f8-1f1e7.svg",
    "country": "Solomon Islands",
    "code": "sb",
    "visa": true,
    "typeVisa": ""
  },
  {
    "flag": "https://twemoji.maxcdn.com/2/svg/1f1f8-1f1e8.svg",
    "country": "Seychelles",
    "code": "sc",
    "visa": false,
    "typeVisa": "90 days free"
  },
  {
    "flag": "https://twemoji.maxcdn.com/2/svg/1f1f8-1f1e9.svg",
    "country": "Sudan",
    "code": "sd",
    "visa": true,
    "typeVisa": ""
  },
  {
    "flag": "https://twemoji.maxcdn.com/2/svg/1f1f8-1f1ea.svg",
    "country": "Sweden",
    "code": "se",
    "visa": true,
    "typeVisa": ""
  },
  {
    "flag": "https://twemoji.maxcdn.com/2/svg/1f1f8-1f1ec.svg",
    "country": "Singapore",
    "code": "sg",
    "visa": false,
    "typeVisa": "90 days free"
  },
  {
    "flag": "https://twemoji.maxcdn.com/2/svg/1f1f8-1f1ed.svg",
    "country": "St. Helena",
    "code": "sh",
    "visa": true,
    "typeVisa": ""
  },
  {
    "flag": "https://twemoji.maxcdn.com/2/svg/1f1f8-1f1ee.svg",
    "country": "Slovenia",
    "code": "si",
    "visa": true,
    "typeVisa": ""
  },
  {
    "flag": "https://twemoji.maxcdn.com/2/svg/1f1f8-1f1ef.svg",
    "country": "Svalbard & Jan Mayen",
    "code": "sj",
    "visa": true,
    "typeVisa": ""
  },
  {
    "flag": "https://twemoji.maxcdn.com/2/svg/1f1f8-1f1f0.svg",
    "country": "Slovakia",
    "code": "sk",
    "visa": true,
    "typeVisa": ""
  },
  {
    "flag": "https://twemoji.maxcdn.com/2/svg/1f1f8-1f1f1.svg",
    "country": "Sierra Leone",
    "code": "sl",
    "visa": true,
    "typeVisa": ""
  },
  {
    "flag": "https://twemoji.maxcdn.com/2/svg/1f1f8-1f1f2.svg",
    "country": "San Marino",
    "code": "sm",
    "visa": false,
    "typeVisa": "90 days free"
  },
  {
    "flag": "https://twemoji.maxcdn.com/2/svg/1f1f8-1f1f3.svg",
    "country": "Senegal",
    "code": "sn",
    "visa": true,
    "typeVisa": ""
  },
  {
    "flag": "https://twemoji.maxcdn.com/2/svg/1f1f8-1f1f4.svg",
    "country": "Somalia",
    "code": "so",
    "visa": true,
    "typeVisa": ""
  },
  {
    "flag": "https://twemoji.maxcdn.com/2/svg/1f1f8-1f1f7.svg",
    "country": "Suriname",
    "code": "sr",
    "visa": false,
    "typeVisa": "90 days free"
  },
  {
    "flag": "https://twemoji.maxcdn.com/2/svg/1f1f8-1f1f8.svg",
    "country": "South Sudan",
    "code": "ss",
    "visa": true,
    "typeVisa": ""
  },
  {
    "flag": "https://twemoji.maxcdn.com/2/svg/1f1f8-1f1f9.svg",
    "country": "São Tomé & Príncipe",
    "code": "st",
    "visa": true,
    "typeVisa": ""
  },
  {
    "flag": "https://twemoji.maxcdn.com/2/svg/1f1f8-1f1fb.svg",
    "country": "El Salvador",
    "code": "sv",
    "visa": false,
    "typeVisa": "90 days free"
  },
  {
    "flag": "https://twemoji.maxcdn.com/2/svg/1f1f8-1f1fd.svg",
    "country": "Sint Maarten",
    "code": "sx",
    "visa": true,
    "typeVisa": ""
  },
  {
    "flag": "https://twemoji.maxcdn.com/2/svg/1f1f8-1f1fe.svg",
    "country": "Syria",
    "code": "sy",
    "visa": true,
    "typeVisa": ""
  },
  {
    "flag": "https://twemoji.maxcdn.com/2/svg/1f1f8-1f1ff.svg",
    "country": "Eswatini",
    "code": "sz",
    "visa": true,
    "typeVisa": ""
  },
  {
    "flag": "https://twemoji.maxcdn.com/2/svg/1f1f9-1f1e6.svg",
    "country": "Tristan Da Cunha",
    "code": "sh",
    "visa": true,
    "typeVisa": ""
  },
  {
    "flag": "https://twemoji.maxcdn.com/2/svg/1f1f9-1f1e8.svg",
    "country": "Turks & Caicos Islands",
    "code": "tc",
    "visa": true,
    "typeVisa": ""
  },
  {
    "flag": "https://twemoji.maxcdn.com/2/svg/1f1f9-1f1e9.svg",
    "country": "Chad",
    "code": "td",
    "visa": true,
    "typeVisa": ""
  },
  {
    "flag": "https://twemoji.maxcdn.com/2/svg/1f1f9-1f1eb.svg",
    "country": "French Southern Territories",
    "code": "tf",
    "visa": true,
    "typeVisa": ""
  },
  {
    "flag": "https://twemoji.maxcdn.com/2/svg/1f1f9-1f1ec.svg",
    "country": "Togo",
    "code": "tg",
    "visa": true,
    "typeVisa": ""
  },
  {
    "flag": "https://twemoji.maxcdn.com/2/svg/1f1f9-1f1ed.svg",
    "country": "Thailand",
    "code": "th",
    "visa": false,
    "typeVisa": "90 days free"
  },
  {
    "flag": "https://twemoji.maxcdn.com/2/svg/1f1f9-1f1ef.svg",
    "country": "Tajikistan",
    "code": "tj",
    "visa": true,
    "typeVisa": ""
  },
  {
    "flag": "https://twemoji.maxcdn.com/2/svg/1f1f9-1f1f0.svg",
    "country": "Tokelau",
    "code": "tk",
    "visa": true,
    "typeVisa": ""
  },
  {
    "flag": "https://twemoji.maxcdn.com/2/svg/1f1f9-1f1f1.svg",
    "country": "Timor-Leste",
    "code": "tl",
    "visa": true,
    "typeVisa": ""
  },
  {
    "flag": "https://twemoji.maxcdn.com/2/svg/1f1f9-1f1f2.svg",
    "country": "Turkmenistan",
    "code": "tm",
    "visa": true,
    "typeVisa": ""
  },
  {
    "flag": "https://twemoji.maxcdn.com/2/svg/1f1f9-1f1f3.svg",
    "country": "Tunisia",
    "code": "tn",
    "visa": false,
    "typeVisa": "90 days free"
  },
  {
    "flag": "https://twemoji.maxcdn.com/2/svg/1f1f9-1f1f4.svg",
    "country": "Tonga",
    "code": "to",
    "visa": true,
    "typeVisa": ""
  },
  {
    "flag": "https://twemoji.maxcdn.com/2/svg/1f1f9-1f1f7.svg",
    "country": "Turkey",
    "code": "tr",
    "visa": false,
    "typeVisa": "90 days free"
  },
  {
    "flag": "https://twemoji.maxcdn.com/2/svg/1f1f9-1f1f9.svg",
    "country": "Trinidad & Tobago",
    "code": "tt",
    "visa": false,
    "typeVisa": "90 days free"
  },
  {
    "flag": "https://twemoji.maxcdn.com/2/svg/1f1f9-1f1fb.svg",
    "country": "Tuvalu",
    "code": "tv",
    "visa": true,
    "typeVisa": ""
  },
  {
    "flag": "https://twemoji.maxcdn.com/2/svg/1f1f9-1f1fc.svg",
    "country": "Taiwan",
    "code": "tw",
    "visa": true,
    "typeVisa": ""
  },
  {
    "flag": "https://twemoji.maxcdn.com/2/svg/1f1f9-1f1ff.svg",
    "country": "Tanzania",
    "code": "tz",
    "visa": true,
    "typeVisa": ""
  },
  {
    "flag": "https://twemoji.maxcdn.com/2/svg/1f1fa-1f1e6.svg",
    "country": "Ukraine",
    "code": "ua",
    "visa": false,
    "typeVisa": "90 days free"
  },
  {
    "flag": "https://twemoji.maxcdn.com/2/svg/1f1fa-1f1ec.svg",
    "country": "Uganda",
    "code": "ug",
    "visa": true,
    "typeVisa": ""
  },
  {
    "flag": "https://twemoji.maxcdn.com/2/svg/1f1fa-1f1f2.svg",
    "country": "U.S. Outlying Islands",
    "code": "um",
    "visa": true,
    "typeVisa": ""
  },
  {
    "flag": "https://twemoji.maxcdn.com/2/svg/1f1fa-1f1f3.svg",
    "country": "United Nations",
    "code": "un",
    "visa": true,
    "typeVisa": ""
  },
  {
    "flag": "https://twemoji.maxcdn.com/2/svg/1f1fa-1f1f8.svg",
    "country": "United States",
    "code": "us",
    "visa": false,
    "typeVisa": "Electronic visa"
  },
  {
    "flag": "https://twemoji.maxcdn.com/2/svg/1f1fa-1f1fe.svg",
    "country": "Uruguay",
    "code": "uy",
    "visa": false,
    "typeVisa": "no Visa"
  },
  {
    "flag": "https://twemoji.maxcdn.com/2/svg/1f1fa-1f1ff.svg",
    "country": "Uzbekistan",
    "code": "uz",
    "visa": true,
    "typeVisa": ""
  },
  {
    "flag": "https://twemoji.maxcdn.com/2/svg/1f1fb-1f1e6.svg",
    "country": "Vatican City",
    "code": "va",
    "visa": false,
    "typeVisa": "90 days free"
  },
  {
    "flag": "https://twemoji.maxcdn.com/2/svg/1f1fb-1f1e8.svg",
    "country": "St. Vincent & Grenadines",
    "code": "vc",
    "visa": true,
    "typeVisa": ""
  },
  {
    "flag": "https://twemoji.maxcdn.com/2/svg/1f1fb-1f1ea.svg",
    "country": "Venezuela",
    "code": "ve",
    "visa": false,
    "typeVisa": "no Visa"
  },
  {
    "flag": "https://twemoji.maxcdn.com/2/svg/1f1fb-1f1ec.svg",
    "country": "British Virgin Islands",
    "code": "vg",
    "visa": true,
    "typeVisa": ""
  },
  {
    "flag": "https://twemoji.maxcdn.com/2/svg/1f1fb-1f1ee.svg",
    "country": "U.S. Virgin Islands",
    "code": "vi",
    "visa": true,
    "typeVisa": ""
  },
  {
    "flag": "https://twemoji.maxcdn.com/2/svg/1f1fb-1f1f3.svg",
    "country": "Vietnam",
    "code": "vn",
    "visa": true,
    "typeVisa": ""
  },
  {
    "flag": "https://twemoji.maxcdn.com/2/svg/1f1fb-1f1fa.svg",
    "country": "Vanuatu",
    "code": "vu",
    "visa": true,
    "typeVisa": ""
  },
  {
    "flag": "https://twemoji.maxcdn.com/2/svg/1f1fc-1f1eb.svg",
    "country": "Wallis & Futuna",
    "code": "wf",
    "visa": true,
    "typeVisa": ""
  },
  {
    "flag": "https://twemoji.maxcdn.com/2/svg/1f1fc-1f1f8.svg",
    "country": "Samoa",
    "code": "ws",
    "visa": true,
    "typeVisa": ""
  },
  {
    "flag": "https://twemoji.maxcdn.com/2/svg/1f1fd-1f1f0.svg",
    "country": "Kosovo",
    "code": "xk",
    "visa": true,
    "typeVisa": ""
  },
  {
    "flag": "https://twemoji.maxcdn.com/2/svg/1f1fe-1f1ea.svg",
    "country": "Yemen",
    "code": "ye",
    "visa": true,
    "typeVisa": ""
  },
  {
    "flag": "https://twemoji.maxcdn.com/2/svg/1f1fe-1f1f9.svg",
    "country": "Mayotte",
    "code": "yt",
    "visa": true,
    "typeVisa": ""
  },
  {
    "flag": "https://twemoji.maxcdn.com/2/svg/1f1ff-1f1e6.svg",
    "country": "South Africa",
    "code": "za",
    "visa": false,
    "typeVisa": "90 days free"
  },
  {
    "flag": "https://twemoji.maxcdn.com/2/svg/1f1ff-1f1f2.svg",
    "country": "Zambia",
    "code": "zm",
    "visa": true,
    "typeVisa": ""
  },
  {
    "flag": "https://twemoji.maxcdn.com/2/svg/1f1ff-1f1fc.svg",
    "country": "Zimbabwe",
    "code": "zw",
    "visa": true,
    "typeVisa": ""
  },
  {
    "flag": "https://twemoji.maxcdn.com/2/svg/1f3f4-e0067-e0062-e0065-e006e-e0067-e007f.svg",
    "country": "England",
    "code": "uk",
    "visa": true,
    "typeVisa": ""
  },
  {
    "flag": "https://twemoji.maxcdn.com/2/svg/1f3f4-e0067-e0062-e0073-e0063-e0074-e007f.svg",
    "country": "Scotland",
    "code": "uk",
    "visa": true,
    "typeVisa": ""
  },
  {
    "flag": "https://twemoji.maxcdn.com/2/svg/1f3f4-e0067-e0062-e0077-e006c-e0073-e007f.svg",
    "country": "Wales",
    "code": "uk",
    "visa": true,
    "typeVisa": ""
  }
]